{"code": "RUSS1151", "title": "Introduction to Russian History & Culture", "activities_michaelmas": [{"code": "LECT/001", "code_long": "RUSS1151/LECT/001", "type": "LECT", "code_info": null, "description": "Introduction to Russian History & Culture", "day": "2019-10-07", "start": "16:00", "end": "17:00", "room": "ER153", "staff": "Dr Alexandra Harrington", "weeks": [0, 1, 2, 3, 4, 5, 6, 7, 8], "planned_size": "33", "id": 0}, {"code": "LECT/002", "code_long": "RUSS1151/LECT/002", "type": "LECT", "code_info": null, "description": "Introduction to Russian History & Culture", "day": "2019-10-07", "start": "16:00", "end": "17:00", "room": "ER153", "staff": "Mrs Olga Zabotkina", "weeks": [9], "planned_size": "33", "id": 1}, {"code": "SEMA/001", "code_long": "RUSS1151/SEMA/001", "type": "SEMA", "code_info": null, "description": "Introduction to Russian History & Culture", "day": "2019-10-10", "start": "09:00", "end": "10:00", "room": "ER206", "staff": "Dr Viktoria Ivleva", "weeks": [1, 3, 5, 7, 9], "planned_size": "20", "id": 2}, {"code": "SEMA/002", "code_long": "RUSS1151/SEMA/002", "type": "SEMA", "code_info": null, "description": "Introduction to Russian History & Culture", "day": "2019-10-10", "start": "10:00", "end": "11:00", "room": "ER206", "staff": "Dr Viktoria Ivleva", "weeks": [1, 3, 5, 7, 9], "planned_size": "20", "id": 3}], "activities_epiphany": [{"code": "LECT/001", "code_long": "RUSS1151/LECT/001", "type": "LECT", "code_info": null, "description": "Introduction to Russian History & Culture", "day": "2020-01-13", "start": "16:00", "end": "17:00", "room": "ER153", "staff": "Dr Alexandra Harrington", "weeks": [0, 1, 2, 3, 4, 5, 6, 7, 8], "planned_size": "33", "id": 0}, {"code": "LECT/002", "code_long": "RUSS1151/LECT/002", "type": "LECT", "code_info": null, "description": "Introduction to Russian History & Culture", "day": "2020-01-13", "start": "16:00", "end": "17:00", "room": "ER153", "staff": "Mrs Olga Zabotkina", "weeks": [9], "planned_size": "33", "id": 1}, {"code": "SEMB/001", "code_long": "RUSS1151/SEMB/001", "type": "SEMB", "code_info": null, "description": "Introduction to Russian History & Culture", "day": "2020-01-16", "start": "09:00", "end": "10:00", "room": "ER206", "staff": "Dr Viktoria Ivleva", "weeks": [1, 3, 5, 7, 9], "planned_size": "16", "id": 2}, {"code": "SEMB/002", "code_long": "RUSS1151/SEMB/002", "type": "SEMB", "code_info": null, "description": "Introduction to Russian History & Culture", "day": "2020-01-16", "start": "10:00", "end": "11:00", "room": "ER206", "staff": "Dr Viktoria Ivleva", "weeks": [1, 3, 5, 7, 9], "planned_size": "16", "id": 3}], "activities_easter": []}