{"code": "ECON434JN", "activities_michaelmas": [], "title": "Experimental Economics and Finance (January Cohort)", "activities_epiphany": [{"code": "LECT/001", "id": 0, "staff": "Professor Jason Shachat", "type": "LECT", "start": "16:00", "weeks": [0, 1, 2, 3, 4], "code_info": "Activity in multiple modules: ECON43415, ECON434JN. Be sure to delete duplicates in other modules.", "room": "\u00a0", "planned_size": "100", "code_long": "ECON43415/LECT/001, ECON434JN/LECT/001", "description": "\u00a0", "end": "18:00", "day": "2021-01-14"}, {"code": "LECT/002", "id": 1, "staff": "Professor Jason Shachat", "type": "LECT", "start": "16:00", "weeks": [5, 6], "code_info": "Activity in multiple modules: ECON43415, ECON434JN. Be sure to delete duplicates in other modules.", "room": "\u00a0", "planned_size": "100", "code_long": "ECON43415/LECT/002, ECON434JN/LECT/002", "description": "\u00a0", "end": "18:00", "day": "2021-01-14"}, {"code": "LECT/003", "id": 2, "staff": "Professor Morten Lau", "type": "LECT", "start": "16:00", "weeks": [7, 8], "code_info": "Activity in multiple modules: ECON43415, ECON434JN. Be sure to delete duplicates in other modules.", "room": "\u00a0", "planned_size": "100", "code_long": "ECON43415/LECT/003, ECON434JN/LECT/003", "description": "\u00a0", "end": "18:00", "day": "2021-01-14"}, {"code": "REVA/01", "id": 3, "staff": "Professor Jason Shachat", "type": "REVA", "start": "16:00", "weeks": [9], "code_info": "Activity in multiple modules: ECON43415, ECON434JN. Be sure to delete duplicates in other modules.", "room": "\u00a0", "planned_size": "100", "code_long": "ECON43415/REVA/001, ECON434JN/REVA/01", "description": "\u00a0", "end": "18:00", "day": "2021-01-14"}], "activities_easter": []}