{"code": "GEOG4137", "title": "Geographies of Life and Living", "activities_michaelmas": [{"code": "SEM/001", "code_long": "GEOG30F7/SEM/001, GEOG4137/SEM/001", "type": "SEM", "code_info": "Activity in multiple modules: GEOG30F7, GEOG4137. Be sure to delete duplicates in other modules.", "description": "\u00a0", "day": "2020-10-08", "start": "09:00", "end": "11:00", "room": "FONTEYN", "staff": "Dr Elizabeth Johnson", "weeks": [0, 1, 2, 4, 5, 7], "planned_size": "48", "id": 0}, {"code": "WORK/001", "code_long": "GEOG30F7/WORK/001, GEOG4137/WORK/001", "type": "WORK", "code_info": "Activity in multiple modules: GEOG30F7, GEOG4137. Be sure to delete duplicates in other modules.", "description": "\u00a0", "day": "2020-10-08", "start": "09:00", "end": "12:00", "room": "FONTEYN", "staff": "Dr Elizabeth Johnson", "weeks": [3, 8], "planned_size": "48", "id": 1}, {"code": "TUT/001", "code_long": "GEOG30F7/TUTA/001, GEOG4137/TUT/001", "type": "TUT", "code_info": "Activity in multiple modules: GEOG30F7, GEOG4137. Be sure to delete duplicates in other modules.", "description": "\u00a0", "day": "2020-10-08", "start": "09:00", "end": "10:00", "room": "\u00a0", "staff": "Dr Elizabeth Johnson", "weeks": [6], "planned_size": "48", "id": 2}, {"code": "TUT/002", "code_long": "GEOG30F7/TUTB/001, GEOG4137/TUT/002", "type": "TUT", "code_info": "Activity in multiple modules: GEOG30F7, GEOG4137. Be sure to delete duplicates in other modules.", "description": "\u00a0", "day": "2020-10-08", "start": "16:00", "end": "17:00", "room": "\u00a0", "staff": "Dr Elizabeth Johnson", "weeks": [6], "planned_size": "48", "id": 3}], "activities_epiphany": [], "activities_easter": []}