{"code": "THEO3501", "title": "Christian Fundamentalism and the Modern World", "activities_michaelmas": [{"code": "SEM/001", "code_long": "THEO3501/SEM/001, THEO45430/LECT/001", "type": "SEM", "code_info": "Activity in multiple modules: THEO3501, THEO45430. Be sure to delete duplicates in other modules.", "description": "\u00a0", "day": "2020-10-05", "start": "15:00", "end": "17:00", "room": "\u00a0", "staff": "Prof Mathew Guest", "weeks": [0, 1, 2, 3, 4, 5, 6, 7, 8, 9], "planned_size": "40", "id": 0}], "activities_epiphany": [{"code": "SEMA/002", "code_long": "THEO3501/SEMA/002", "type": "SEMA", "code_info": null, "description": "Christian Fundamentalism and the Modern World", "day": "2021-01-11", "start": "10:00", "end": "11:00", "room": "\u00a0", "staff": "Prof Mathew Guest", "weeks": [5, 6, 7, 8, 9], "planned_size": "12", "id": 0}, {"code": "SEMA/001", "code_long": "THEO3501/SEMA/001", "type": "SEMA", "code_info": null, "description": "Christian Fundamentalism and the Modern World", "day": "2021-01-11", "start": "11:00", "end": "12:00", "room": "PG21", "staff": "Prof Mathew Guest", "weeks": [5, 6, 7, 8, 9], "planned_size": "12", "id": 1}, {"code": "SEM/001", "code_long": "THEO3501/SEM/001, THEO45430/LECT/001", "type": "SEM", "code_info": "Activity in multiple modules: THEO3501, THEO45430. Be sure to delete duplicates in other modules.", "description": "\u00a0", "day": "2021-01-11", "start": "15:00", "end": "17:00", "room": "\u00a0", "staff": "Prof Mathew Guest", "weeks": [0, 1, 2, 3, 4, 5, 6, 7, 8, 9], "planned_size": "40", "id": 2}, {"code": "SEMA/003", "code_long": "THEO3501/SEMA/003", "type": "SEMA", "code_info": null, "description": "Christian Fundamentalism and the Modern World", "day": "2021-01-15", "start": "17:00", "end": "18:00", "room": "ED101", "staff": "Prof Mathew Guest", "weeks": [5, 6, 7, 8, 9], "planned_size": "12", "id": 3}], "activities_easter": [{"code": "SEM/001", "code_long": "THEO3501/SEM/001, THEO45430/LECT/001", "type": "SEM", "code_info": "Activity in multiple modules: THEO3501, THEO45430. Be sure to delete duplicates in other modules.", "description": "\u00a0", "day": "2021-04-26", "start": "15:00", "end": "17:00", "room": "\u00a0", "staff": "Prof Mathew Guest", "weeks": [0, 1], "planned_size": "40", "id": 0}]}