{"code": "ARCH54530", "title": "Museum Principles and Practice", "activities_michaelmas": [{"code": "LECT/001", "code_long": "ARCH54530/LECT/001", "type": "LECT", "code_info": null, "description": "Museum Principles and Practice", "day": "2020-10-08", "start": "09:00", "end": "11:00", "room": "CLC013", "staff": "Dr Ben Roberts", "weeks": [0, 1, 2, 3, 4, 5, 6, 7, 8, 9], "planned_size": "34", "id": 0}], "activities_epiphany": [{"code": "LECT/001", "code_long": "ARCH54530/LECT/001", "type": "LECT", "code_info": null, "description": "Museum Principles and Practice", "day": "2021-01-14", "start": "09:00", "end": "11:00", "room": "CLC013", "staff": "Dr Ben Roberts", "weeks": [0, 1, 2, 3, 4, 5, 6, 7, 8, 9], "planned_size": "34", "id": 0}], "activities_easter": []}