{"activities_easter": [{"code": "LECTA/001", "code_info": null, "code_long": "BUSI48W15/LECTA/001", "day": "2022-04-25", "description": "Green Supply Chain and Logistics Systems", "end": "18:00", "id": 0, "planned_size": "75", "room": "BUSC454", "staff": "Dr Manish Shukla", "start": "16:00", "type": "LECTA", "weeks": [0]}, {"code": "SEMA/001", "code_info": null, "code_long": "BUSI48W15/SEMA/001", "day": "2022-04-26", "description": "Green Supply Chain and Logistics Systems", "end": "14:00", "id": 1, "planned_size": "75", "room": "BUSC454", "staff": "Dr Manish Shukla", "start": "13:00", "type": "SEMA", "weeks": [0]}], "activities_epiphany": [{"code": "LECTA/001", "code_info": null, "code_long": "BUSI48W15/LECTA/001", "day": "2022-01-10", "description": "Green Supply Chain and Logistics Systems", "end": "18:00", "id": 0, "planned_size": "75", "room": "BUSC454", "staff": "Dr Manish Shukla", "start": "16:00", "type": "LECTA", "weeks": [8, 9]}, {"code": "SEMA/001", "code_info": null, "code_long": "BUSI48W15/SEMA/001", "day": "2022-01-11", "description": "Green Supply Chain and Logistics Systems", "end": "14:00", "id": 1, "planned_size": "75", "room": "BUSC454", "staff": "Dr Manish Shukla", "start": "13:00", "type": "SEMA", "weeks": [8, 9]}], "activities_michaelmas": [{"code": "SEM/001", "code_info": null, "code_long": "BUSI48W15/SEM/001", "day": "2021-10-05", "description": "Green Supply Chain and Logistics Systems", "end": "18:00", "id": 0, "planned_size": "25", "room": "BUSC453", "staff": "Dr Manish Shukla", "start": "17:00", "type": "SEM", "weeks": [2, 4, 6, 8]}, {"code": "SEM/003", "code_info": null, "code_long": "BUSI48W15/SEM/003", "day": "2021-10-07", "description": "Green Supply Chain and Logistics Systems", "end": "12:00", "id": 1, "planned_size": "25", "room": "BUSC453", "staff": "Dr Manish Shukla", "start": "11:00", "type": "SEM", "weeks": [2, 4, 6, 8]}, {"code": "SEM/002", "code_info": null, "code_long": "BUSI48W15/SEM/002", "day": "2021-10-07", "description": "Green Supply Chain and Logistics Systems", "end": "15:00", "id": 2, "planned_size": "25", "room": "BUSC223", "staff": "Dr Manish Shukla", "start": "14:00", "type": "SEM", "weeks": [3, 5, 7, 9]}, {"code": "LECT/001", "code_info": null, "code_long": "BUSI48W15/LECT/001", "day": "2021-10-08", "description": "Green Supply Chain and Logistics Systems", "end": "16:00", "id": 3, "planned_size": "75", "room": "BUSC454", "staff": "Dr Manish Shukla", "start": "14:00", "type": "LECT", "weeks": [0, 1, 2, 3, 4, 5, 6, 7, 8]}], "code": "BUSI48W15", "title": "Sustainable Supply Chain Management"}