{"code": "COMP3467", "activities_michaelmas": [], "title": "Advanced Computer Systems", "activities_epiphany": [{"code": "LECT/001", "id": 0, "staff": "Dr Steven Bradley", "type": "LECT", "start": "10:00", "weeks": [0, 1, 2, 3, 4, 5, 6, 7, 8, 9], "code_info": null, "room": "\u00a0", "planned_size": "80", "code_long": "COMP3467/LECT/001", "description": "Advanced Computer Systems", "end": "11:00", "day": "2021-01-11"}, {"code": "LECT/002", "id": 1, "staff": "Dr Steven Bradley", "type": "LECT", "start": "11:00", "weeks": [0, 1, 2, 3, 4, 5, 6, 7, 8, 9], "code_info": null, "room": "\u00a0", "planned_size": "80", "code_long": "COMP3467/LECT/002", "description": "Advanced Computer Systems", "end": "12:00", "day": "2021-01-13"}], "activities_easter": [{"code": "LECT/001", "id": 0, "staff": "Dr Steven Bradley", "type": "LECT", "start": "10:00", "weeks": [0, 1], "code_info": null, "room": "\u00a0", "planned_size": "80", "code_long": "COMP3467/LECT/001", "description": "Advanced Computer Systems", "end": "11:00", "day": "2021-04-26"}, {"code": "LECT/002", "id": 1, "staff": "Dr Steven Bradley", "type": "LECT", "start": "11:00", "weeks": [0, 1], "code_info": null, "room": "\u00a0", "planned_size": "80", "code_long": "COMP3467/LECT/002", "description": "Advanced Computer Systems", "end": "12:00", "day": "2021-04-28"}]}