{"activities_easter": [], "activities_epiphany": [{"code": "MLECT/102", "code_info": null, "code_long": "LANG41815/MLECT/102", "day": "2021-01-11", "description": "Teaching Young Learners", "end": "16:00", "id": 0, "planned_size": "60", "room": "\u00a0", "staff": "Ms Sylvie Donna", "start": "14:00", "type": "MLECT", "weeks": [0, 1, 2, 3, 4, 6, 7, 8, 9]}, {"code": "MLECT/101", "code_info": null, "code_long": "LANG41815/MLECT/101", "day": "2021-01-13", "description": "Teaching Young Learners", "end": "11:00", "id": 1, "planned_size": "60", "room": "\u00a0", "staff": "Ms Sylvie Donna", "start": "09:00", "type": "MLECT", "weeks": [0, 1, 2, 3, 4, 6, 7, 8, 9]}, {"code": "SEMA/001", "code_info": null, "code_long": "LANG41815/SEMA/001", "day": "2021-01-15", "description": "Teaching Young Learners", "end": "16:00", "id": 2, "planned_size": "42", "room": "\u00a0", "staff": "Ms Sylvie Donna", "start": "14:00", "type": "SEMA", "weeks": [6]}, {"code": "SEM/001", "code_info": null, "code_long": "LANG41815/SEM/001", "day": "2021-01-15", "description": "Teaching Young Learners", "end": "18:00", "id": 3, "planned_size": "42", "room": "\u00a0", "staff": "Ms Sylvie Donna", "start": "16:00", "type": "SEM", "weeks": [3]}, {"code": "SEM/002", "code_info": null, "code_long": "LANG41815/SEM/002", "day": "2021-01-15", "description": "Teaching Young Learners", "end": "18:00", "id": 4, "planned_size": "40", "room": "\u00a0", "staff": "Ms Sylvie Donna", "start": "16:00", "type": "SEM", "weeks": [4]}, {"code": "SEMA/002", "code_info": null, "code_long": "LANG41815/SEMA/002", "day": "2021-01-15", "description": "Teaching Young Learners", "end": "18:00", "id": 5, "planned_size": "39", "room": "\u00a0", "staff": "Ms Sylvie Donna", "start": "16:00", "type": "SEMA", "weeks": [6]}], "activities_michaelmas": [], "code": "LANG41815", "title": "Teaching Young Learners"}