{"activities_easter": [], "activities_epiphany": [], "activities_michaelmas": [{"code": "LECT/001", "code_info": null, "code_long": "ANTH2217/LECT/001", "day": "2020-10-05", "description": "Debating Anthropology and Archaeology", "end": "10:00", "id": 0, "planned_size": "20", "room": "\u00a0", "staff": "Dr Trudi Buck,Dr Catherine Draycott,Dr Marta Diaz-Guardamino,Dr Elizabeth Kirtsoglou,Dr Rebecca Gowland,Dr Jamie Tehrani,Professor Mark White,Professor Sarah Elton", "start": "09:00", "type": "LECT", "weeks": [0, 1, 2, 4, 5, 7, 8]}, {"code": "TUT/001(NPC)", "code_info": null, "code_long": "ANTH2217/TUT/001(NPC)", "day": "2020-10-05", "description": "Debating Anthropology and Archaeology", "end": "11:00", "id": 1, "planned_size": "20", "room": "\u00a0", "staff": "Dr Trudi Buck,Dr Marta Diaz-Guardamino", "start": "09:00", "type": "TUT", "weeks": [3, 6, 9]}], "code": "ANTH2217", "title": "Debating Anthropology & Archaeology"}