{"code": "BIOL40140", "activities_michaelmas": [{"code": "LECT/012", "id": 0, "staff": "Dr Philip Stephens", "type": "LECT", "start": "09:00", "weeks": [3], "code_info": "Activity in multiple modules: BIOL40140, BIOL4121. Be sure to delete duplicates in other modules.", "room": "\u00a0", "planned_size": "33", "code_long": "BIOL40140/LECT/012, BIOL4121/LECT/012", "description": "\u00a0", "end": "12:00", "day": "2020-10-05"}, {"code": "LECT/015", "id": 1, "staff": "\u00a0", "type": "LECT", "start": "09:00", "weeks": [7], "code_info": "Activity in multiple modules: BIOL40140, BIOL4121. Be sure to delete duplicates in other modules.", "room": "\u00a0", "planned_size": "33", "code_long": "BIOL40140/LECT/015, BIOL4121/LECT/015", "description": "\u00a0", "end": "11:00", "day": "2020-10-05"}, {"code": "LECT/019", "id": 2, "staff": "Dr Robert Baxter", "type": "LECT", "start": "09:00", "weeks": [8], "code_info": "Activity in multiple modules: BIOL40140, BIOL4121. Be sure to delete duplicates in other modules.", "room": "\u00a0", "planned_size": "33", "code_long": "BIOL40140/LECT/019, BIOL4121/LECT/019", "description": "\u00a0", "end": "11:00", "day": "2020-10-05"}, {"code": "SEM/002", "id": 3, "staff": "Biolguestlecturer01", "type": "SEM", "start": "16:00", "weeks": [1, 3, 5, 7], "code_info": "Activity in multiple modules: BIOL3451, BIOL40140, BIOL4121. Be sure to delete duplicates in other modules.", "room": "\u00a0", "planned_size": "140", "code_long": "BIOL3451/SEM/002, BIOL40140/SEM/002, BIOL4121/SEM/002(NP)", "description": "\u00a0", "end": "17:00", "day": "2020-10-06"}, {"code": "SEM/001", "id": 4, "staff": "Biolguestlecturer01", "type": "SEM", "start": "16:00", "weeks": [2, 4, 6, 8], "code_info": "Activity in multiple modules: BIOL3451, BIOL40140, BIOL4121. Be sure to delete duplicates in other modules.", "room": "\u00a0", "planned_size": "190", "code_long": "BIOL3451/SEM/001, BIOL40140/SEM/001, BIOL4121/SEM/001", "description": "\u00a0", "end": "17:00", "day": "2020-10-06"}, {"code": "LECT/101", "id": 5, "staff": "Dr Heather Knight", "type": "LECT", "start": "09:00", "weeks": [0], "code_info": "Activity in multiple modules: BIOL40140, BIOL4121. Be sure to delete duplicates in other modules.", "room": "\u00a0", "planned_size": "60", "code_long": "BIOL40140/LECT/101, BIOL4121/LECT/101", "description": "\u00a0", "end": "12:00", "day": "2020-10-07"}, {"code": "LECT/005", "id": 6, "staff": "Dr Jennifer Topping", "type": "LECT", "start": "09:00", "weeks": [5], "code_info": "Activity in multiple modules: BIOL40140, BIOL4121. Be sure to delete duplicates in other modules.", "room": "\u00a0", "planned_size": "33", "code_long": "BIOL40140/LECT/005, BIOL4121/LECT/005", "description": "\u00a0", "end": "11:00", "day": "2020-10-07"}, {"code": "LECT/006", "id": 7, "staff": "Professor Colin Jahoda", "type": "LECT", "start": "09:00", "weeks": [6], "code_info": "Activity in multiple modules: BIOL40140, BIOL4121. Be sure to delete duplicates in other modules.", "room": "\u00a0", "planned_size": "33", "code_long": "BIOL40140/LECT/006, BIOL4121/LECT/006", "description": "\u00a0", "end": "11:00", "day": "2020-10-07"}, {"code": "LECT/007", "id": 8, "staff": "Dr Steve Chivasa", "type": "LECT", "start": "09:00", "weeks": [7], "code_info": "Activity in multiple modules: BIOL40140, BIOL4121. Be sure to delete duplicates in other modules.", "room": "\u00a0", "planned_size": "33", "code_long": "BIOL40140/LECT/007, BIOL4121/LECT/007", "description": "\u00a0", "end": "11:00", "day": "2020-10-07"}, {"code": "LECT/008", "id": 9, "staff": "Dr Timothy Hawkins", "type": "LECT", "start": "09:00", "weeks": [8], "code_info": "Activity in multiple modules: BIOL40140, BIOL4121. Be sure to delete duplicates in other modules.", "room": "\u00a0", "planned_size": "33", "code_long": "BIOL40140/LECT/008, BIOL4121/LECT/008", "description": "\u00a0", "end": "11:00", "day": "2020-10-07"}, {"code": "LECT/009", "id": 10, "staff": "Dr Timothy Hawkins", "type": "LECT", "start": "09:00", "weeks": [9], "code_info": "Activity in multiple modules: BIOL40140, BIOL4121. Be sure to delete duplicates in other modules.", "room": "\u00a0", "planned_size": "33", "code_long": "BIOL40140/LECT/009, BIOL4121/LECT/009", "description": "\u00a0", "end": "11:00", "day": "2020-10-07"}, {"code": "LECT/003", "id": 11, "staff": "Dr Adrian C Brennan", "type": "LECT", "start": "10:00", "weeks": [3], "code_info": "Activity in multiple modules: BIOL40140, BIOL4121. Be sure to delete duplicates in other modules.", "room": "\u00a0", "planned_size": "33", "code_long": "BIOL40140/LECT/003, BIOL4121/LECT/003", "description": "\u00a0", "end": "11:00", "day": "2020-10-07"}, {"code": "LECT/103", "id": 12, "staff": "Dr Sean Twiss", "type": "LECT", "start": "12:00", "weeks": [0], "code_info": "Activity in multiple modules: BIOL40140, BIOL4121. Be sure to delete duplicates in other modules.", "room": "\u00a0", "planned_size": "30", "code_long": "BIOL40140/LECT/103, BIOL4121/LECT/103", "description": "\u00a0", "end": "13:00", "day": "2020-10-07"}, {"code": "LECT/102", "id": 13, "staff": "Dr Heather Knight", "type": "LECT", "start": "12:00", "weeks": [0], "code_info": "Activity in multiple modules: BIOL40140, BIOL4121. Be sure to delete duplicates in other modules.", "room": "\u00a0", "planned_size": "60", "code_long": "BIOL40140/LECT/102, BIOL4121/LECT/102", "description": "\u00a0", "end": "13:00", "day": "2020-10-07"}, {"code": "LECT/104", "id": 14, "staff": "Biolguestlecturer01", "type": "LECT", "start": "14:00", "weeks": [0], "code_info": "Activity in multiple modules: BIOL40140, BIOL4121. Be sure to delete duplicates in other modules.", "room": "\u00a0", "planned_size": "60", "code_long": "BIOL40140/LECT/104, BIOL4121/LECT/104", "description": "\u00a0", "end": "15:00", "day": "2020-10-07"}, {"code": "LECT/112", "id": 15, "staff": "Dr Heather Knight", "type": "LECT", "start": "09:00", "weeks": [0], "code_info": "Activity in multiple modules: BIOL40140, BIOL4121. Be sure to delete duplicates in other modules.", "room": "\u00a0", "planned_size": "60", "code_long": "BIOL40140/LECT/112, BIOL4121/LECT/112", "description": "\u00a0", "end": "17:00", "day": "2020-10-08"}, {"code": "LECT/004", "id": 16, "staff": "Dr John Bothwell", "type": "LECT", "start": "09:00", "weeks": [4], "code_info": "Activity in multiple modules: BIOL40140, BIOL4121. Be sure to delete duplicates in other modules.", "room": "\u00a0", "planned_size": "33", "code_long": "BIOL40140/LECT/004, BIOL4121/LECT/004", "description": "\u00a0", "end": "11:00", "day": "2020-10-09"}], "title": "Principles and Research practice in the Biological Sciences", "activities_epiphany": [{"code": "LECT/010", "id": 0, "staff": "Dr Martin Goldberg", "type": "LECT", "start": "09:00", "weeks": [1], "code_info": "Activity in multiple modules: BIOL40140, BIOL4121. Be sure to delete duplicates in other modules.", "room": "\u00a0", "planned_size": "33", "code_long": "BIOL40140/LECT/010, BIOL4121/LECT/010", "description": "\u00a0", "end": "11:00", "day": "2021-01-11"}, {"code": "LECT/018", "id": 1, "staff": "\u00a0", "type": "LECT", "start": "09:00", "weeks": [2], "code_info": "Activity in multiple modules: BIOL40140, BIOL4121. Be sure to delete duplicates in other modules.", "room": "\u00a0", "planned_size": "33", "code_long": "BIOL40140/LECT/018, BIOL4121/LECT/018", "description": "\u00a0", "end": "11:00", "day": "2021-01-11"}, {"code": "PRAC/001", "id": 2, "staff": "Dr Martin Goldberg", "type": "PRAC", "start": "11:00", "weeks": [1], "code_info": "Activity in multiple modules: BIOL40140, BIOL4121. Be sure to delete duplicates in other modules.", "room": "BL136/3", "planned_size": "6", "code_long": "BIOL40140/PRAC/001, BIOL4121/PRAC/001", "description": "\u00a0", "end": "13:00", "day": "2021-01-11"}, {"code": "SEM/002", "id": 3, "staff": "Biolguestlecturer01", "type": "SEM", "start": "16:00", "weeks": [0, 2, 4, 6, 8], "code_info": "Activity in multiple modules: BIOL3451, BIOL40140, BIOL4121. Be sure to delete duplicates in other modules.", "room": "\u00a0", "planned_size": "140", "code_long": "BIOL3451/SEM/002, BIOL40140/SEM/002, BIOL4121/SEM/002(NP)", "description": "\u00a0", "end": "17:00", "day": "2021-01-12"}, {"code": "SEM/001", "id": 4, "staff": "Biolguestlecturer01", "type": "SEM", "start": "16:00", "weeks": [1, 3, 5, 7, 9], "code_info": "Activity in multiple modules: BIOL3451, BIOL40140, BIOL4121. Be sure to delete duplicates in other modules.", "room": "\u00a0", "planned_size": "190", "code_long": "BIOL3451/SEM/001, BIOL40140/SEM/001, BIOL4121/SEM/001", "description": "\u00a0", "end": "17:00", "day": "2021-01-12"}, {"code": "LECT/021", "id": 5, "staff": "Dr Angus Rosenburgh", "type": "LECT", "start": "09:00", "weeks": [0], "code_info": "Activity in multiple modules: BIOL40140, BIOL4121. Be sure to delete duplicates in other modules.", "room": "\u00a0", "planned_size": "33", "code_long": "BIOL40140/LECT/021, BIOL4121/LECT/021", "description": "\u00a0", "end": "11:00", "day": "2021-01-13"}, {"code": "LECT/014", "id": 6, "staff": "Dr Junli Liu", "type": "LECT", "start": "09:00", "weeks": [1], "code_info": "Activity in multiple modules: BIOL40140, BIOL4121. Be sure to delete duplicates in other modules.", "room": "\u00a0", "planned_size": "33", "code_long": "BIOL40140/LECT/014, BIOL4121/LECT/014", "description": "\u00a0", "end": "11:00", "day": "2021-01-13"}, {"code": "LECT/013", "id": 7, "staff": "Dr Adrian C Brennan", "type": "LECT", "start": "09:00", "weeks": [2], "code_info": "Activity in multiple modules: BIOL40140, BIOL4121. Be sure to delete duplicates in other modules.", "room": "\u00a0", "planned_size": "33", "code_long": "BIOL40140/LECT/013, BIOL4121/LECT/013", "description": "\u00a0", "end": "11:00", "day": "2021-01-13"}, {"code": "LECT/017", "id": 8, "staff": "Dr Sean Twiss", "type": "LECT", "start": "09:00", "weeks": [1], "code_info": "Activity in multiple modules: BIOL40140, BIOL4121. Be sure to delete duplicates in other modules.", "room": "\u00a0", "planned_size": "33", "code_long": "BIOL40140/LECT/017, BIOL4121/LECT/017", "description": "\u00a0", "end": "11:00", "day": "2021-01-14"}], "activities_easter": [{"code": "SEM/001", "id": 0, "staff": "Biolguestlecturer01", "type": "SEM", "start": "16:00", "weeks": [1], "code_info": "Activity in multiple modules: BIOL3451, BIOL40140, BIOL4121. Be sure to delete duplicates in other modules.", "room": "\u00a0", "planned_size": "190", "code_long": "BIOL3451/SEM/001, BIOL40140/SEM/001, BIOL4121/SEM/001", "description": "\u00a0", "end": "17:00", "day": "2021-04-27"}, {"code": "PRES/001", "id": 1, "staff": "Dr Jennifer Topping", "type": "PRES", "start": "09:00", "weeks": [1], "code_info": "Activity in multiple modules: BIOL40140, BIOL4121. Be sure to delete duplicates in other modules.", "room": "\u00a0", "planned_size": "56", "code_long": "BIOL40140/PRES/001, BIOL4121/PRES/001", "description": "\u00a0", "end": "17:00", "day": "2021-04-28"}]}