{"code": "CLAS3612", "title": "Dissertation (40 Credits)", "activities_michaelmas": [{"code": "SEM/001", "code_long": "CLAS3612/SEM/001", "type": "SEM", "code_info": null, "description": "Dissertation (40 Credits)", "day": "2019-10-07", "start": "15:00", "end": "17:45", "room": "\u00a0", "staff": "Dr Edmund Richardson,Dr Phillip Horky,Professor Jennifer Ingleheart,Dr Amy Russell,Dr George Gazis,Dr Stuart Mckie", "weeks": [0, 1], "planned_size": "27", "id": 0}, {"code": "SEM/002", "code_long": "CLAS3612/SEM/002", "type": "SEM", "code_info": null, "description": "Dissertation (40 Credits)", "day": "2019-10-09", "start": "09:00", "end": "11:45", "room": "\u00a0", "staff": "Dr Edmund Richardson,Dr Kathryn Stevens,Professor Jennifer Ingleheart,Dr Amy Russell,Dr Edmund Thomas", "weeks": [0, 1], "planned_size": "27", "id": 1}, {"code": "DISC/001", "code_long": "CLAS3612/DISC/001", "type": "DISC", "code_info": null, "description": "Dissertation (40 Credits) Discussion Class", "day": "2019-10-10", "start": "13:00", "end": "14:00", "room": "\u00a0", "staff": "Dr Edmund Richardson,Dr Phillip Horky,Dr Kathryn Stevens,Dr Amy Russell,Dr George Gazis,Dr Stuart Mckie", "weeks": [0, 1, 2, 3, 4, 5, 6, 7, 8, 9], "planned_size": "108", "id": 2}, {"code": "SEM/003", "code_long": "CLAS3612/SEM/003", "type": "SEM", "code_info": null, "description": "Dissertation (40 Credits)", "day": "2019-10-10", "start": "15:00", "end": "17:45", "room": "\u00a0", "staff": "\u00a0", "weeks": [0, 1], "planned_size": "27", "id": 3}, {"code": "SEM/004", "code_long": "CLAS3612/SEM/004", "type": "SEM", "code_info": null, "description": "Dissertation (40 Credits)", "day": "2019-10-11", "start": "15:00", "end": "17:45", "room": "\u00a0", "staff": "Dr Kathryn Stevens,Dr Amy Russell,Dr George Gazis,Dr Stuart Mckie", "weeks": [0, 1], "planned_size": "27", "id": 4}], "activities_epiphany": [{"code": "ADD/001", "code_long": "CLAS3612/ADD/001", "type": "ADD", "code_info": null, "description": "Dissertation (40 Credits) Additional Class", "day": "2020-01-16", "start": "13:00", "end": "14:00", "room": "\u00a0", "staff": "Dr Edmund Richardson,Dr Phillip Horky,Dr Amy Russell", "weeks": [0, 1, 2, 3, 5, 6, 7, 8, 9], "planned_size": "108", "id": 0}, {"code": "ADD/002", "code_long": "CLAS3612/ADD/002", "type": "ADD", "code_info": null, "description": "Dissertation (40 Credits)", "day": "2020-01-16", "start": "13:00", "end": "14:00", "room": "D/ER140", "staff": "\u00a0", "weeks": [4], "planned_size": "88", "id": 1}], "activities_easter": []}